<?xml version="1.0" encoding="utf-8"?>
<!DOCTYPE documentInfo>
<documentInfo url="/Respaldo/BMC/Second/3DComputerVision/3D_CV_ST_2012_CameraModels_II.pdf">
 <pageList/>
 <generalInfo>
  <history>
   <oldPage viewport="34;C2:0.499424:0.115207:1"/>
   <oldPage viewport="33;C2:0.499424:0.304147:1"/>
   <oldPage viewport="32;C2:0.499424:0.0322581:1"/>
   <oldPage viewport="31;C2:0.499424:0.0368664:1"/>
   <oldPage viewport="30;C2:0.499424:0.225806:1"/>
   <oldPage viewport="29;C2:0.499424:0.0460829:1"/>
   <oldPage viewport="28;C2:0.499424:0.235023:1"/>
   <oldPage viewport="27;C2:0.499424:0.0552995:1"/>
   <oldPage viewport="26;C2:0.499424:0.0599078:1"/>
   <oldPage viewport="25;C2:0.499424:0.0645161:1"/>
   <current viewport="24;C2:0.499424:0.898618:1"/>
  </history>
  <views>
   <view name="PageView">
    <zoom mode="2" value="1.20556"/>
   </view>
  </views>
 </generalInfo>
</documentInfo>
